print.py
setup.py
test_print.py
HelloWorldHelloWorldHello-1.0.0.dist-info/METADATA
HelloWorldHelloWorldHello-1.0.0.dist-info/WHEEL
HelloWorldHelloWorldHello-1.0.0.dist-info/top_level.txt
HelloWorldHelloWorldHello-1.0.0.dist-info/RECORD
