Metadata-Version: 2.1
Name: HelloWorldHelloWorldHello
Version: 1.0.0
Summary: A simple Python project
Author: Your Name
Author-email: your.email@example.com
Requires-Dist: numpy
Requires-Dist: pandas
